[   
    {
        "id": 1,
        "name": "T-Shirt",
        "price": "$40.00",
        "images":[
            {
                "url": "https://github.com/naejshaw/Portfolio-11/blob/acd7ff6154609cb06d88d65a08f1328f312849c6/src/img/T-shirt-black.png",
                "color": "#272727"
            },
            {
                "url": "src/img/T-shirt-darkblue.png",
                "color": "#23284E"
            }
        ]
    },

    {
        "id": 2,
        "name": "Oversize T-Shirt",
        "price": "$52.99",
        "images":[
            {
                "url": "src/img/oversize-T-shirt-black.png",
                "color": "#272727"
            }
        ]
    },

    {
        "id": 3,
        "name": "Sweater",
        "price": "$69.99",
        "images":[
            {
                "url": "src/img/sweater.png",
                "color": "#272727"
            }
        ]
    }
]
